rustic_ai/showcase/__init__.py
rustic_ai/showcase/google/__init__.py
rustic_ai/showcase/google/fact_checker.py
rustic_ai/showcase/laira/__init__.py
rustic_ai/showcase/laira/research_manager.py
rusticai_showcase-1.0.0.dist-info/METADATA
rusticai_showcase-1.0.0.dist-info/WHEEL
rusticai_showcase-1.0.0.dist-info/RECORD
