Metadata-Version: 2.4
Name: rusticai-showcase
Version: 1.0.0
Summary: Module that showcases Rustic AI capabilities
License-Expression: Apache-2.0
Author: Dragonscale Industries Inc.
Author-email: dev@dragonscale.ai
Requires-Python: >=3.12,<3.13
Classifier: Programming Language :: Python :: 3
Classifier: Programming Language :: Python :: 3.12
Provides-Extra: test
Requires-Dist: google-api-python-client (>=2.187.0,<3.0.0)
Requires-Dist: rusticai-chroma (>=1.0.0,<1.1.0)
Requires-Dist: rusticai-core (>=1.0.0,<1.1.0)
Requires-Dist: rusticai-langchain (>=1.0.0,<1.1.0)
Requires-Dist: rusticai-litellm (>=1.0.0,<1.1.0)
Requires-Dist: rusticai-playwright (>=1.0.0,<1.1.0)
Requires-Dist: rusticai-serpapi (>=1.0.0,<1.1.0)
Requires-Dist: rusticai-vertexai (>=1.0.0,<1.1.0)
Requires-Dist: spacytextblob (>=5.1.0,<6.0.0)
Project-URL: Homepage, https://www.rustic.ai/
Project-URL: Repository, https://github.com/rustic-ai/rustic-ai
Project-URL: Rustic AI Core, https://pypi.org/project/rusticai-core/
